HtmlRumenjiaochengCYuyanBianchengWangFix1/README.md
HtmlRumenjiaochengCYuyanBianchengWangFix1/__init__.py
HtmlRumenjiaochengCYuyanBianchengWangFix1/__main__.py
HtmlRumenjiaochengCYuyanBianchengWangFix1/file.epub
HtmlRumenjiaochengCYuyanBianchengWangFix1/index.html
HtmlRumenjiaochengCYuyanBianchengWangFix1/css/__init__.py
HtmlRumenjiaochengCYuyanBianchengWangFix1/css/annotations.css
HtmlRumenjiaochengCYuyanBianchengWangFix1/css/main.css
HtmlRumenjiaochengCYuyanBianchengWangFix1/css/normalize.css
HtmlRumenjiaochengCYuyanBianchengWangFix1/css/popup.css
HtmlRumenjiaochengCYuyanBianchengWangFix1/font/__init__.py
HtmlRumenjiaochengCYuyanBianchengWangFix1/font/fontello.eot
HtmlRumenjiaochengCYuyanBianchengWangFix1/font/fontello.svg
HtmlRumenjiaochengCYuyanBianchengWangFix1/font/fontello.ttf
HtmlRumenjiaochengCYuyanBianchengWangFix1/font/fontello.woff
HtmlRumenjiaochengCYuyanBianchengWangFix1/img/__init__.py
HtmlRumenjiaochengCYuyanBianchengWangFix1/img/annotator-glyph-sprite.png
HtmlRumenjiaochengCYuyanBianchengWangFix1/img/annotator-icon-sprite.png
HtmlRumenjiaochengCYuyanBianchengWangFix1/img/apple-touch-icon.png
HtmlRumenjiaochengCYuyanBianchengWangFix1/img/cancelfullscreen.png
HtmlRumenjiaochengCYuyanBianchengWangFix1/img/close.png
HtmlRumenjiaochengCYuyanBianchengWangFix1/img/fullscreen.png
HtmlRumenjiaochengCYuyanBianchengWangFix1/img/loader.gif
HtmlRumenjiaochengCYuyanBianchengWangFix1/img/menu-icon.png
HtmlRumenjiaochengCYuyanBianchengWangFix1/img/save.png
HtmlRumenjiaochengCYuyanBianchengWangFix1/img/saved.png
HtmlRumenjiaochengCYuyanBianchengWangFix1/img/settings-s.png
HtmlRumenjiaochengCYuyanBianchengWangFix1/img/settings.png
HtmlRumenjiaochengCYuyanBianchengWangFix1/img/star.png
HtmlRumenjiaochengCYuyanBianchengWangFix1/js/__init__.py
HtmlRumenjiaochengCYuyanBianchengWangFix1/js/epub.js
HtmlRumenjiaochengCYuyanBianchengWangFix1/js/epub.min.js
HtmlRumenjiaochengCYuyanBianchengWangFix1/js/epub.min.map
HtmlRumenjiaochengCYuyanBianchengWangFix1/js/hooks.min.js
html_rumenjiaocheng_c_yuyan_biancheng_wang_fix1-2025.3.24.0.dist-info/METADATA
html_rumenjiaocheng_c_yuyan_biancheng_wang_fix1-2025.3.24.0.dist-info/WHEEL
html_rumenjiaocheng_c_yuyan_biancheng_wang_fix1-2025.3.24.0.dist-info/entry_points.txt
html_rumenjiaocheng_c_yuyan_biancheng_wang_fix1-2025.3.24.0.dist-info/top_level.txt
html_rumenjiaocheng_c_yuyan_biancheng_wang_fix1-2025.3.24.0.dist-info/RECORD
